pilotcmd/__init__.py
pilotcmd/__main__.py
pilotcmd/cli.py
pilotcmd/config/__init__.py
pilotcmd/config/manager.py
pilotcmd/context_db/__init__.py
pilotcmd/context_db/manager.py
pilotcmd/executor/__init__.py
pilotcmd/executor/command_executor.py
pilotcmd/models/__init__.py
pilotcmd/models/base.py
pilotcmd/models/factory.py
pilotcmd/models/ollama_model.py
pilotcmd/models/openai_model.py
pilotcmd/nlp/__init__.py
pilotcmd/nlp/parser.py
pilotcmd/nlp/simple_parser.py
pilotcmd/os_utils/__init__.py
pilotcmd/os_utils/detector.py
pilotcmd-0.1.0.dist-info/METADATA
pilotcmd-0.1.0.dist-info/WHEEL
pilotcmd-0.1.0.dist-info/entry_points.txt
pilotcmd-0.1.0.dist-info/top_level.txt
pilotcmd-0.1.0.dist-info/RECORD
